azure/synapse/accesscontrol/__init__.py
azure/synapse/accesscontrol/_access_control_client.py
azure/synapse/accesscontrol/_configuration.py
azure/synapse/accesscontrol/_version.py
azure/synapse/accesscontrol/py.typed
azure/synapse/accesscontrol/aio/__init__.py
azure/synapse/accesscontrol/aio/_access_control_client.py
azure/synapse/accesscontrol/aio/_configuration.py
azure/synapse/accesscontrol/aio/operations/__init__.py
azure/synapse/accesscontrol/aio/operations/_access_control_client_operations.py
azure/synapse/accesscontrol/aio/operations/_role_assignments_operations.py
azure/synapse/accesscontrol/aio/operations/_role_definitions_operations.py
azure/synapse/accesscontrol/models/__init__.py
azure/synapse/accesscontrol/models/_models.py
azure/synapse/accesscontrol/models/_models_py3.py
azure/synapse/accesscontrol/operations/__init__.py
azure/synapse/accesscontrol/operations/_access_control_client_operations.py
azure/synapse/accesscontrol/operations/_role_assignments_operations.py
azure/synapse/accesscontrol/operations/_role_definitions_operations.py
azure_synapse_accesscontrol-0.7.0.dist-info/METADATA
azure_synapse_accesscontrol-0.7.0.dist-info/WHEEL
azure_synapse_accesscontrol-0.7.0.dist-info/top_level.txt
azure_synapse_accesscontrol-0.7.0.dist-info/RECORD
